md4mathjax/__init__.py
md4mathjax/md4mathjax.py
md4mathjax-0.1.3.dist-info/LICENSE
md4mathjax-0.1.3.dist-info/METADATA
md4mathjax-0.1.3.dist-info/WHEEL
md4mathjax-0.1.3.dist-info/entry_points.txt
md4mathjax-0.1.3.dist-info/top_level.txt
md4mathjax-0.1.3.dist-info/RECORD
